LICENSE
MANIFEST.in
README.md
setup.py
cortex/__init__.py
cortex/calls.py
cortex/file_manip.py
cortex/settings.py
cortex/utils.py
cortex/ext/install_dependencies.sh
cortex/ext/minimap2
cortex/ext/cortex/.gitignore
cortex/ext/cortex/.hgignore
cortex/ext/cortex/INSTALL
cortex/ext/cortex/Makefile
cortex/ext/cortex/README.md
cortex/ext/cortex/ReleaseNotes
cortex/ext/cortex/gpl.txt
cortex/ext/cortex/install.sh
cortex/ext/cortex/latest_test_results
cortex/ext/cortex/.git/HEAD
cortex/ext/cortex/.git/config
cortex/ext/cortex/.git/description
cortex/ext/cortex/.git/index
cortex/ext/cortex/.git/packed-refs
cortex/ext/cortex/.git/hooks/applypatch-msg.sample
cortex/ext/cortex/.git/hooks/commit-msg.sample
cortex/ext/cortex/.git/hooks/fsmonitor-watchman.sample
cortex/ext/cortex/.git/hooks/post-update.sample
cortex/ext/cortex/.git/hooks/pre-applypatch.sample
cortex/ext/cortex/.git/hooks/pre-commit.sample
cortex/ext/cortex/.git/hooks/pre-merge-commit.sample
cortex/ext/cortex/.git/hooks/pre-push.sample
cortex/ext/cortex/.git/hooks/pre-rebase.sample
cortex/ext/cortex/.git/hooks/pre-receive.sample
cortex/ext/cortex/.git/hooks/prepare-commit-msg.sample
cortex/ext/cortex/.git/hooks/update.sample
cortex/ext/cortex/.git/info/exclude
cortex/ext/cortex/.git/logs/HEAD
cortex/ext/cortex/.git/logs/refs/heads/master
cortex/ext/cortex/.git/logs/refs/remotes/origin/HEAD
cortex/ext/cortex/.git/objects/pack/pack-43b7c8476cf6e28cb553b96918a079b09ead4fd9.idx
cortex/ext/cortex/.git/objects/pack/pack-43b7c8476cf6e28cb553b96918a079b09ead4fd9.pack
cortex/ext/cortex/.git/refs/heads/master
cortex/ext/cortex/.git/refs/remotes/origin/HEAD
cortex/ext/cortex/bin/cortex_var_31_c1
cortex/ext/cortex/bin/cortex_var_31_c2
cortex/ext/cortex/data/test/basic/includes_final_read_that_has_bad_characters.fa
cortex/ext/cortex/data/test/basic/includes_multiline_reads.fq
cortex/ext/cortex/data/test/basic/includes_one_read_that_is_too_long.fq
py_cortex_api.egg-info/PKG-INFO
py_cortex_api.egg-info/SOURCES.txt
py_cortex_api.egg-info/dependency_links.txt
py_cortex_api.egg-info/requires.txt
py_cortex_api.egg-info/top_level.txt