Metadata-Version: 2.1
Name: py-cortex-api
Version: 2.2.1
Summary: Python API for cortex.
Home-page: https://github.com/iqbal-lab-org/py-cortex-api
License: UNKNOWN
Platform: UNKNOWN
